modelkit/__init__.py
modelkit/api.py
modelkit/cli.py
modelkit/py.typed
modelkit/assets/__init__.py
modelkit/assets/cli.py
modelkit/assets/errors.py
modelkit/assets/manager.py
modelkit/assets/remote.py
modelkit/assets/settings.py
modelkit/assets/drivers/__init__.py
modelkit/assets/drivers/abc.py
modelkit/assets/drivers/azure.py
modelkit/assets/drivers/gcs.py
modelkit/assets/drivers/local.py
modelkit/assets/drivers/retry.py
modelkit/assets/drivers/s3.py
modelkit/assets/versioning/__init__.py
modelkit/assets/versioning/major_minor.py
modelkit/assets/versioning/simple_date.py
modelkit/assets/versioning/versioning.py
modelkit/core/__init__.py
modelkit/core/errors.py
modelkit/core/library.py
modelkit/core/model.py
modelkit/core/model_configuration.py
modelkit/core/settings.py
modelkit/core/types.py
modelkit/core/models/__init__.py
modelkit/core/models/distant_model.py
modelkit/core/models/tensorflow_model.py
modelkit/core/profilers/__init__.py
modelkit/core/profilers/base.py
modelkit/core/profilers/simple.py
modelkit/testing/__init__.py
modelkit/testing/fixtures.py
modelkit/testing/reference.py
modelkit/testing/tf_serving.py
modelkit/utils/__init__.py
modelkit/utils/cache.py
modelkit/utils/logging.py
modelkit/utils/memory.py
modelkit/utils/pretty.py
modelkit/utils/redis.py
modelkit/utils/serialization.py
modelkit/utils/tensorflow.py
modelkit-0.1.3.dist-info/LICENSE
modelkit-0.1.3.dist-info/METADATA
modelkit-0.1.3.dist-info/WHEEL
modelkit-0.1.3.dist-info/entry_points.txt
modelkit-0.1.3.dist-info/top_level.txt
modelkit-0.1.3.dist-info/RECORD
