Metadata-Version: 2.2
Name: modelkit
Version: 0.1.3
Summary: Minimalistic MLOps library for python
Project-URL: Homepage, https://github.com/Cornerstone-OnDemand/modelkit
Project-URL: Bug Tracker, https://github.com/Cornerstone-OnDemand/modelkit/issues
Project-URL: Documentation, https://Cornerstone-OnDemand.github.io/modelkit/
Project-URL: Source Code, https://github.com/Cornerstone-OnDemand/modelkit
Classifier: Programming Language :: Python :: 3
Classifier: Programming Language :: Python :: 3.8
Classifier: Programming Language :: Python :: 3.9
Classifier: Programming Language :: Python :: 3.10
Classifier: Programming Language :: Python :: 3.11
Requires-Python: >=3.8
License-File: LICENSE
Requires-Dist: aiohttp
Requires-Dist: asgiref
Requires-Dist: cachetools
Requires-Dist: click
Requires-Dist: filelock
Requires-Dist: humanize
Requires-Dist: pydantic>=2.0
Requires-Dist: pydantic-settings
Requires-Dist: python-dateutil
Requires-Dist: redis
Requires-Dist: requests
Requires-Dist: rich
Requires-Dist: sniffio
Requires-Dist: structlog
Requires-Dist: tenacity
Requires-Dist: typing_extensions
Requires-Dist: tabulate
Provides-Extra: tensorflow
Requires-Dist: numpy; extra == "tensorflow"
Requires-Dist: grpcio; extra == "tensorflow"
Requires-Dist: tensorflow; extra == "tensorflow"
Requires-Dist: tensorflow-serving-api; extra == "tensorflow"
Provides-Extra: cli
Requires-Dist: networkx; extra == "cli"
Requires-Dist: memory-profiler; extra == "cli"
Requires-Dist: fastapi; extra == "cli"
Requires-Dist: uvicorn; extra == "cli"
Provides-Extra: api
Requires-Dist: fastapi; extra == "api"
Requires-Dist: uvicorn; extra == "api"
Provides-Extra: assets-s3
Requires-Dist: boto3; extra == "assets-s3"
Provides-Extra: assets-gcs
Requires-Dist: google-cloud-storage; extra == "assets-gcs"
Provides-Extra: assets-az
Requires-Dist: azure-storage-blob; extra == "assets-az"
Requires-Dist: cryptography>=41.0.2; extra == "assets-az"
Provides-Extra: lint
Requires-Dist: black; extra == "lint"
Requires-Dist: flake8; extra == "lint"
Requires-Dist: ruff; extra == "lint"
Requires-Dist: mypy; extra == "lint"
Requires-Dist: types-requests; extra == "lint"
Requires-Dist: types-python-dateutil; extra == "lint"
Requires-Dist: types-cachetools; extra == "lint"
Requires-Dist: types-redis; extra == "lint"
Requires-Dist: types-tabulate; extra == "lint"
Provides-Extra: dev
Requires-Dist: httpx; extra == "dev"
Requires-Dist: mypy; extra == "dev"
Requires-Dist: types-requests; extra == "dev"
Requires-Dist: types-python-dateutil; extra == "dev"
Requires-Dist: types-cachetools; extra == "dev"
Requires-Dist: types-redis; extra == "dev"
Requires-Dist: types-tabulate; extra == "dev"
Requires-Dist: pre-commit; extra == "dev"
Requires-Dist: coverage; extra == "dev"
Requires-Dist: pytest; extra == "dev"
Requires-Dist: pytest-asyncio; extra == "dev"
Requires-Dist: pytest-timeout; extra == "dev"
Requires-Dist: nox; extra == "dev"
Requires-Dist: bump-my-version; extra == "dev"
Requires-Dist: mkdocs-material; extra == "dev"
Requires-Dist: pymdown-extensions>=10.0; extra == "dev"
Requires-Dist: wheel>=0.38.1; extra == "dev"
Requires-Dist: pip-tools; extra == "dev"
